{
    "swagger": "2.0",
    "info": {
        "title": "API da Loja virtual",
        "description": "Documentação da API",
        "version": "1.0.0"
    },
    "host": "http://localhost:3333",
    "basePath": "/",
    "schemes": [
        "http"
    ],
    "paths": {
        "/v1/produto/": {
            "get": {
                "description": "",
                "responses": {
                    "default": {
                        "description": ""
                    }
                }
            },
            "post": {
                "description": "",
                "responses": {
                    "default": {
                        "description": ""
                    }
                }
            }
        },
        "/v1/produto/{id}": {
            "get": {
                "description": "",
                "parameters": [
                    {
                        "name": "id",
                        "in": "path",
                        "required": true,
                        "type": "string"
                    }
                ],
                "responses": {
                    "default": {
                        "description": ""
                    }
                }
            },
            "put": {
                "description": "",
                "parameters": [
                    {
                        "name": "id",
                        "in": "path",
                        "required": true,
                        "type": "string"
                    }
                ],
                "responses": {
                    "default": {
                        "description": ""
                    }
                }
            },
            "delete": {
                "description": "",
                "parameters": [
                    {
                        "name": "id",
                        "in": "path",
                        "required": true,
                        "type": "string"
                    }
                ],
                "responses": {
                    "default": {
                        "description": ""
                    }
                }
            }
        },
        "/v1/signup": {
            "post": {
                "description": "",
                "responses": {
                    "default": {
                        "description": ""
                    }
                }
            }
        },
        "/v1/login": {
            "post": {
                "description": "",
                "parameters": [
                    {
                        "name": "body",
                        "in": "body",
                        "schema": {
                            "type": "object",
                            "properties": {
                                "email": {
                                    "example": "any"
                                },
                                "senha": {
                                    "example": "any"
                                }
                            }
                        }
                    }
                ],
                "responses": {
                    "default": {
                        "description": ""
                    }
                }
            }
        },
        "/v1/logout": {
            "post": {
                "description": "",
                "responses": {
                    "default": {
                        "description": ""
                    }
                }
            }
        },
        "/v1/language/": {
            "post": {
                "description": "",
                "parameters": [
                    {
                        "name": "body",
                        "in": "body",
                        "schema": {
                            "type": "object",
                            "properties": {
                                "lang": {
                                    "example": "any"
                                }
                            }
                        }
                    }
                ],
                "responses": {
                    "default": {
                        "description": ""
                    }
                }
            }
        },
        "/v1/usuario/": {
            "get": {
                "description": "",
                "responses": {
                    "default": {
                        "description": ""
                    }
                }
            },
            "post": {
                "description": "",
                "responses": {
                    "default": {
                        "description": ""
                    }
                }
            }
        },
        "/v1/usuario/{id}": {
            "get": {
                "description": "",
                "parameters": [
                    {
                        "name": "id",
                        "in": "path",
                        "required": true,
                        "type": "string"
                    }
                ],
                "responses": {
                    "default": {
                        "description": ""
                    }
                }
            },
            "put": {
                "description": "",
                "parameters": [
                    {
                        "name": "id",
                        "in": "path",
                        "required": true,
                        "type": "string"
                    }
                ],
                "responses": {
                    "default": {
                        "description": ""
                    }
                }
            },
            "delete": {
                "description": "",
                "parameters": [
                    {
                        "name": "id",
                        "in": "path",
                        "required": true,
                        "type": "string"
                    }
                ],
                "responses": {
                    "default": {
                        "description": ""
                    }
                }
            }
        },
        "/v1/": {
            "get": {
                "description": "",
                "responses": {
                    "200": {
                        "description": "OK"
                    }
                }
            }
        },
        "/v1/sobre": {
            "get": {
                "description": "",
                "responses": {
                    "200": {
                        "description": "OK"
                    }
                }
            }
        },
        "/v1/bemvindo/{nome}": {
            "get": {
                "description": "",
                "parameters": [
                    {
                        "name": "nome",
                        "in": "path",
                        "required": true,
                        "type": "string"
                    }
                ],
                "responses": {
                    "default": {
                        "description": ""
                    }
                }
            }
        },
        "/v1/{(api|resResponset)\\}/.$/": {
            "get": {
                "description": "",
                "parameters": [
                    {
                        "name": "(api|resResponset)\\",
                        "in": "path",
                        "required": true,
                        "type": "string"
                    }
                ],
                "responses": {
                    "200": {
                        "description": "OK"
                    }
                }
            }
        },
        "/v1/lorem/{qtd}": {
            "get": {
                "description": "",
                "parameters": [
                    {
                        "name": "qtd",
                        "in": "path",
                        "required": true,
                        "type": "string"
                    }
                ],
                "responses": {
                    "200": {
                        "description": "OK"
                    }
                }
            }
        }
    }
}
